{"bill":{"bill_id":1647669,"change_hash":"001ffec061aac4de10b438a3ac46d48d","session_id":2034,"session":{"session_id":2034,"state_id":37,"year_start":2023,"year_end":2023,"prefile":0,"sine_die":0,"prior":0,"special":0,"session_tag":"Regular Session","session_title":"2023 Regular Session","session_name":"2023 Legislative Measures"},"url":"https:\/\/legiscan.com\/OR\/bill\/HB2115\/2023","state_link":"https:\/\/olis.oregonlegislature.gov\/liz\/2023R1\/Measures\/Overview\/HB2115","completed":0,"status":1,"status_date":"2023-01-09","progress":[{"date":"2023-01-09","event":1},{"date":"2023-01-12","event":9}],"state":"OR","state_id":37,"bill_number":"HB2115","bill_type":"B","bill_type_id":"1","body":"H","body_id":81,"current_body":"H","current_body_id":81,"title":"Relating to small business.","description":"Directs Secretary of State to study small business conducted in Oregon and to report to Legislative Assembly on findings of study. Directs Secretary of State to study small business conducted in Oregon and to report to Legislative Assembly on findings of study.","pending_committee_id":4705,"committee":{"committee_id":4705,"chamber":"H","chamber_id":81,"name":"Economic Development and Small Business"},"referrals":[{"date":"2023-01-12","committee_id":4705,"chamber":"H","chamber_id":81,"name":"Economic Development and Small Business"}],"history":[{"date":"2023-01-09","action":"First reading. Referred to Speaker's desk.","chamber":"H","chamber_id":81,"importance":1},{"date":"2023-01-12","action":"Referred to Economic Development and Small Business.","chamber":"H","chamber_id":81,"importance":1}],"sponsors":[],"sasts":[],"subjects":[],"texts":[{"doc_id":2627712,"date":"0000-00-00","type":"Introduced","type_id":1,"mime":"application\/pdf","mime_id":2,"url":"https:\/\/legiscan.com\/OR\/text\/HB2115\/id\/2627712","state_link":"https:\/\/olis.oregonlegislature.gov\/liz\/2023R1\/Downloads\/MeasureDocument\/HB2115\/Introduced","text_size":26172,"text_hash":"ca0f4f50d175ddcbe408e61631caf6a2"}],"votes":[],"amendments":[],"supplements":[],"calendar":[]}}