{"bill":{"bill_id":1684728,"change_hash":"c864d0f77357ff5eec854818c79cdb24","session_id":2030,"session":{"session_id":2030,"state_id":31,"year_start":2023,"year_end":2023,"prefile":0,"sine_die":0,"prior":0,"special":0,"session_tag":"Regular Session","session_title":"2023 Regular Session","session_name":"2023 Regular Session"},"url":"https:\/\/legiscan.com\/NM\/bill\/HB218\/2023","state_link":"https:\/\/www.nmlegis.gov\/Legislation\/Legislation?chamber=H&legtype=B&legno=218&year=23","completed":0,"status":1,"status_date":"2023-01-27","progress":[{"date":"2023-01-27","event":1},{"date":"2023-02-13","event":10}],"state":"NM","state_id":31,"bill_number":"HB218","bill_type":"B","bill_type_id":"1","body":"H","body_id":71,"current_body":"H","current_body_id":71,"title":"Low-income Public Utility Rates","description":"Low-income Public Utility Rates","pending_committee_id":2176,"committee":{"committee_id":2176,"chamber":"H","chamber_id":71,"name":"Judiciary"},"referrals":[{"date":"2023-01-27","committee_id":2170,"chamber":"H","chamber_id":71,"name":"Consumer & Public Affairs"}],"history":[{"date":"2023-01-27","action":"Sent to HCPAC - Referrals: HCPAC\/HJC","chamber":"H","chamber_id":71,"importance":0},{"date":"2023-02-13","action":"HCPAC: Reported by committee with Do Pass recommendation with amendment(s)","chamber":"H","chamber_id":71,"importance":1}],"sponsors":[],"sasts":[],"subjects":[],"texts":[{"doc_id":2668410,"date":"2023-01-27","type":"Introduced","type_id":1,"mime":"application\/pdf","mime_id":2,"url":"https:\/\/legiscan.com\/NM\/text\/HB218\/id\/2668410","state_link":"https:\/\/www.nmlegis.gov\/Sessions\/23%20Regular\/bills\/house\/HB0218.pdf","text_size":130490,"text_hash":"7732ed1aca992455ef41b97765c5447d"}],"votes":[],"amendments":[],"supplements":[],"calendar":[{"type_id":1,"type":"Hearing","date":"2023-02-09","time":"13:30","location":"Room 317","description":"House Consumer & Public Affairs Committee"},{"type_id":1,"type":"Hearing","date":"2023-02-22","time":"13:30","location":"Room 309","description":"House Judiciary Committee"},{"type_id":1,"type":"Hearing","date":"2023-02-24","time":"13:30","location":"Room 309","description":"House Judiciary Committee"}]}}