{"bill":{"bill_id":1689260,"change_hash":"add2e919ef0309c3670d3ceb9c0df0b9","session_id":2030,"session":{"session_id":2030,"state_id":31,"year_start":2023,"year_end":2023,"prefile":0,"sine_die":0,"prior":0,"special":0,"session_tag":"Regular Session","session_title":"2023 Regular Session","session_name":"2023 Regular Session"},"url":"https:\/\/legiscan.com\/NM\/bill\/HB256\/2023","state_link":"https:\/\/www.nmlegis.gov\/Legislation\/Legislation?chamber=H&legtype=B&legno=256&year=23","completed":0,"status":1,"status_date":"2023-01-31","progress":[{"date":"2023-01-31","event":1},{"date":"2023-02-13","event":10}],"state":"NM","state_id":31,"bill_number":"HB256","bill_type":"B","bill_type_id":"1","body":"H","body_id":71,"current_body":"H","current_body_id":71,"title":"Hybrid Dual Credit Pilot Project","description":"Hybrid Dual Credit Pilot Project","pending_committee_id":2167,"committee":{"committee_id":2167,"chamber":"H","chamber_id":71,"name":"Appropriations & Finance"},"referrals":[{"date":"2023-01-31","committee_id":2173,"chamber":"H","chamber_id":71,"name":"Education"}],"history":[{"date":"2023-01-31","action":"Sent to HEC - Referrals: HEC\/HAFC","chamber":"H","chamber_id":71,"importance":0},{"date":"2023-02-13","action":"HEC: Reported by committee with Do Pass recommendation","chamber":"H","chamber_id":71,"importance":1}],"sponsors":[],"sasts":[],"subjects":[],"texts":[{"doc_id":2673848,"date":"2023-01-31","type":"Introduced","type_id":1,"mime":"application\/pdf","mime_id":2,"url":"https:\/\/legiscan.com\/NM\/text\/HB256\/id\/2673848","state_link":"https:\/\/www.nmlegis.gov\/Sessions\/23%20Regular\/bills\/house\/HB0256.pdf","text_size":129597,"text_hash":"02efceb27fa9a94fd237ee8967e1fec6"}],"votes":[],"amendments":[],"supplements":[],"calendar":[{"type_id":1,"type":"Hearing","date":"2023-02-13","time":"08:30","location":"Room 309","description":"House Education Committee"},{"type_id":1,"type":"Hearing","date":"2023-02-27","time":"13:30","location":"Room 307","description":"House Appropriations & Finance Committee"}]}}