{"bill":{"bill_id":1696901,"change_hash":"ab8ff834ba33d9c7979bdafcdbf4658a","session_id":2030,"session":{"session_id":2030,"state_id":31,"year_start":2023,"year_end":2023,"prefile":0,"sine_die":0,"prior":0,"special":0,"session_tag":"Regular Session","session_title":"2023 Regular Session","session_name":"2023 Regular Session"},"url":"https:\/\/legiscan.com\/NM\/bill\/SB344\/2023","state_link":"https:\/\/www.nmlegis.gov\/Legislation\/Legislation?chamber=S&legtype=B&legno=344&year=23","completed":0,"status":1,"status_date":"2023-02-06","progress":[{"date":"2023-02-06","event":1}],"state":"NM","state_id":31,"bill_number":"SB344","bill_type":"B","bill_type_id":"1","body":"S","body_id":72,"current_body":"S","current_body_id":72,"title":"Small Business Development Center Program","description":"Small Business Development Center Program","pending_committee_id":2187,"committee":{"committee_id":2187,"chamber":"S","chamber_id":72,"name":"Education"},"referrals":[{"date":"2023-02-06","committee_id":2187,"chamber":"S","chamber_id":72,"name":"Education"}],"history":[{"date":"2023-02-06","action":"Sent to SEC - Referrals: SEC\/SFC","chamber":"S","chamber_id":72,"importance":0}],"sponsors":[],"sasts":[],"subjects":[],"texts":[{"doc_id":2684013,"date":"2023-02-06","type":"Introduced","type_id":1,"mime":"application\/pdf","mime_id":2,"url":"https:\/\/legiscan.com\/NM\/text\/SB344\/id\/2684013","state_link":"https:\/\/www.nmlegis.gov\/Sessions\/23%20Regular\/bills\/senate\/SB0344.pdf","text_size":111639,"text_hash":"16244cdda2c9a54a37330ae6f2d6e73d"}],"votes":[],"amendments":[],"supplements":[],"calendar":[{"type_id":1,"type":"Hearing","date":"2023-02-13","time":"09:00","location":"Room 311","description":"Senate Education Committee"},{"type_id":1,"type":"Hearing","date":"2023-02-15","time":"08:30","location":"Room 311","description":"Senate Education Committee"}]}}