{"bill":{"bill_id":1639728,"change_hash":"a1dcb49009a9faaaa5a24b7b46dd6f13","session_id":1978,"session":{"session_id":1978,"state_id":44,"year_start":2023,"year_end":2023,"prefile":0,"sine_die":0,"prior":0,"special":0,"session_tag":"Regular Session","session_title":"2023 Regular Session","session_name":"2023 General Session"},"url":"https:\/\/legiscan.com\/UT\/bill\/HB0065\/2023","state_link":"https:\/\/le.utah.gov\/~2023\/bills\/static\/HB0065.html","completed":0,"status":2,"status_date":"2023-01-24","progress":[{"date":"2023-01-17","event":1},{"date":"2023-01-17","event":9},{"date":"2023-01-19","event":10},{"date":"2023-01-24","event":2},{"date":"2023-01-25","event":9},{"date":"2023-01-26","event":10}],"state":"UT","state_id":44,"bill_number":"HB0065","bill_type":"B","bill_type_id":"1","body":"H","body_id":93,"current_body":"H","current_body_id":93,"title":"Division of Technology Services Amendments","description":"Division of Technology Services Amendments","pending_committee_id":0,"committee":[],"referrals":[{"date":"2023-01-17","committee_id":2116,"chamber":"H","chamber_id":93,"name":"Rules"},{"date":"2023-01-17","committee_id":2107,"chamber":"H","chamber_id":93,"name":"Government Operations"},{"date":"2023-01-24","committee_id":2128,"chamber":"S","chamber_id":94,"name":"Rules"},{"date":"2023-01-25","committee_id":2122,"chamber":"S","chamber_id":94,"name":"Government Operations and Political Subdivisions"}],"history":[{"date":"2022-12-21","action":"Bill Numbered but not Distributed in Legislative Research and General Counsel","chamber":"","chamber_id":0,"importance":0},{"date":"2022-12-21","action":"Numbered Bill Publicly Distributed in Legislative Research and General Counsel","chamber":"","chamber_id":0,"importance":0},{"date":"2022-12-21","action":"LFA\/ bill sent to agencies for fiscal input in Legislative Research and General Counsel","chamber":"","chamber_id":0,"importance":0},{"date":"2023-01-04","action":"House\/ received bill from Legislative Research in Clerk of the House","chamber":"H","chamber_id":93,"importance":0},{"date":"2023-01-13","action":"LFA\/ fiscal note sent to sponsor in Clerk of the House","chamber":"H","chamber_id":93,"importance":0},{"date":"2023-01-13","action":"LFA\/ fiscal note publicly available in Clerk of the House","chamber":"H","chamber_id":93,"importance":0},{"date":"2023-01-17","action":"House\/ received fiscal note from Fiscal Analyst in Clerk of the House","chamber":"H","chamber_id":93,"importance":0},{"date":"2023-01-17","action":"House\/ 1st reading (Introduced) in House Rules Committee","chamber":"H","chamber_id":93,"importance":1},{"date":"2023-01-17","action":"House\/ to standing committee in House Government Operations Committee","chamber":"H","chamber_id":93,"importance":1},{"date":"2023-01-18","action":"House Comm - Favorable Recommendation in House Government Operations Committee","chamber":"H","chamber_id":93,"importance":0},{"date":"2023-01-19","action":"House\/ committee report favorable in House Government Operations Committee","chamber":"H","chamber_id":93,"importance":1},{"date":"2023-01-19","action":"House\/ 2nd reading in House 3rd Reading Calendar for House bills","chamber":"H","chamber_id":93,"importance":0},{"date":"2023-01-19","action":"House\/ 3rd reading in House 3rd Reading Calendar for House bills","chamber":"H","chamber_id":93,"importance":0},{"date":"2023-01-19","action":"House\/ passed 3rd reading in Senate Secretary","chamber":"S","chamber_id":94,"importance":0},{"date":"2023-01-19","action":"House\/ held in House Docket Clerk","chamber":"H","chamber_id":93,"importance":0},{"date":"2023-01-23","action":"House\/ to Senate in Senate Secretary","chamber":"S","chamber_id":94,"importance":0},{"date":"2023-01-24","action":"Senate\/ received from House in Waiting for Introduction in the Senate","chamber":"S","chamber_id":94,"importance":1},{"date":"2023-01-24","action":"Senate\/ 1st reading (Introduced) in Senate Rules Committee","chamber":"S","chamber_id":94,"importance":0},{"date":"2023-01-25","action":"Senate\/ to standing committee in Senate Government Operations and Political Subdivisions Committee","chamber":"S","chamber_id":94,"importance":1},{"date":"2023-01-25","action":"Senate Comm - Favorable Recommendation in Senate Government Operations and Political Subdivisions Committee","chamber":"S","chamber_id":94,"importance":0},{"date":"2023-01-26","action":"Senate\/ committee report favorable in Senate Government Operations and Political Subdivisions Committee","chamber":"S","chamber_id":94,"importance":1},{"date":"2023-01-26","action":"Senate\/ placed on 2nd Reading Calendar in Senate 2nd Reading Calendar","chamber":"S","chamber_id":94,"importance":0},{"date":"2023-02-01","action":"Senate\/ 2nd reading in Senate 2nd Reading Calendar","chamber":"S","chamber_id":94,"importance":0},{"date":"2023-02-01","action":"Senate\/ circled in Senate 2nd Reading Calendar","chamber":"S","chamber_id":94,"importance":0},{"date":"2023-02-09","action":"Senate\/ uncircled in Senate 2nd Reading Calendar","chamber":"S","chamber_id":94,"importance":0},{"date":"2023-02-09","action":"Senate\/ passed 2nd reading in Senate 3rd Reading Calendar","chamber":"S","chamber_id":94,"importance":0},{"date":"2023-02-10","action":"Senate\/ 3rd reading in Senate 3rd Reading Calendar","chamber":"S","chamber_id":94,"importance":0},{"date":"2023-02-10","action":"Senate\/ passed 3rd reading in Senate President","chamber":"S","chamber_id":94,"importance":0},{"date":"2023-02-10","action":"Senate\/ signed by President\/ returned to House in House Speaker","chamber":"H","chamber_id":93,"importance":0},{"date":"2023-02-10","action":"Senate\/ to House in House Speaker","chamber":"H","chamber_id":93,"importance":0},{"date":"2023-02-13","action":"House\/ received from Senate in House Speaker","chamber":"H","chamber_id":93,"importance":0},{"date":"2023-02-13","action":"House\/ signed by Speaker\/ sent for enrolling in Legislative Research and General Counsel \/ Enrolling","chamber":"","chamber_id":0,"importance":0},{"date":"2023-02-14","action":"Bill Received from House for Enrolling in Legislative Research and General Counsel \/ Enrolling","chamber":"","chamber_id":0,"importance":0},{"date":"2023-02-14","action":"Draft of Enrolled Bill Prepared in Legislative Research and General Counsel \/ Enrolling","chamber":"","chamber_id":0,"importance":0}],"sponsors":[{"people_id":20382,"person_hash":"35363c2e","party_id":"2","state_id":44,"party":"R","role_id":1,"role":"Rep","name":"Jeffrey Stenquist","first_name":"Jeffrey","middle_name":"D.","last_name":"Stenquist","suffix":"","nickname":"Jeff","district":"HD-051","ftm_eid":45078738,"votesmart_id":114157,"opensecrets_id":"","knowwho_pid":659538,"ballotpedia":"Jeff_Stenquist","bioguide_id":"","sponsor_type_id":1,"sponsor_order":1,"committee_sponsor":0,"committee_id":0,"state_federal":0},{"people_id":20381,"person_hash":"ypls84pj","party_id":"1","state_id":44,"party":"D","role_id":2,"role":"Sen","name":"Stephanie Pitcher","first_name":"Stephanie","middle_name":"","last_name":"Pitcher","suffix":"","nickname":"","district":"SD-014","ftm_eid":45142643,"votesmart_id":182179,"opensecrets_id":"","knowwho_pid":659462,"ballotpedia":"Stephanie_Pitcher","bioguide_id":"","sponsor_type_id":3,"sponsor_order":2,"committee_sponsor":0,"committee_id":0,"state_federal":0}],"sasts":[],"subjects":[{"subject_id":354084,"subject_name":"Division of Technology Services"},{"subject_id":11851,"subject_name":"Government Operations (State Issues)"},{"subject_id":334542,"subject_name":"Agency Technology Services and Public Websites"},{"subject_id":11871,"subject_name":"Business"},{"subject_id":360912,"subject_name":"Public Utilities and Technology"},{"subject_id":354066,"subject_name":"Department of Government Operations"},{"subject_id":354115,"subject_name":"Procurement"}],"texts":[{"doc_id":2619818,"date":"2022-12-21","type":"Introduced","type_id":1,"mime":"application\/pdf","mime_id":2,"url":"https:\/\/legiscan.com\/UT\/text\/HB0065\/id\/2619818","state_link":"https:\/\/le.utah.gov\/~2023\/bills\/hbillint\/HB0065.pdf","text_size":125701,"text_hash":"0a51e4b816d507fa2c4a75d109210c99"}],"votes":[{"roll_call_id":1232694,"date":"2023-01-18","desc":"House Comm - Favorable Recommendation","yea":8,"nay":0,"nv":0,"absent":4,"total":12,"passed":1,"chamber":"H","chamber_id":93,"url":"https:\/\/legiscan.com\/UT\/rollcall\/HB0065\/id\/1232694","state_link":"https:\/\/le.utah.gov\/mtgvotes.jsp?voteid=25553"},{"roll_call_id":1233300,"date":"2023-01-19","desc":"House\/ passed 3rd reading","yea":67,"nay":0,"nv":0,"absent":7,"total":74,"passed":1,"chamber":"H","chamber_id":93,"url":"https:\/\/legiscan.com\/UT\/rollcall\/HB0065\/id\/1233300","state_link":"https:\/\/le.utah.gov\/DynaBill\/svotes.jsp?sessionid=2023GS&voteid=46&house=H"},{"roll_call_id":1235623,"date":"2023-01-25","desc":"Senate Comm - Favorable Recommendation","yea":5,"nay":0,"nv":0,"absent":3,"total":8,"passed":1,"chamber":"S","chamber_id":94,"url":"https:\/\/legiscan.com\/UT\/rollcall\/HB0065\/id\/1235623","state_link":"https:\/\/le.utah.gov\/mtgvotes.jsp?voteid=25953"},{"roll_call_id":1247302,"date":"2023-02-09","desc":"Senate\/ passed 2nd reading","yea":28,"nay":0,"nv":0,"absent":1,"total":29,"passed":1,"chamber":"S","chamber_id":94,"url":"https:\/\/legiscan.com\/UT\/rollcall\/HB0065\/id\/1247302","state_link":"https:\/\/le.utah.gov\/DynaBill\/svotes.jsp?sessionid=2023GS&voteid=475&house=S"},{"roll_call_id":1247970,"date":"2023-02-10","desc":"Senate\/ passed 3rd reading","yea":24,"nay":0,"nv":0,"absent":5,"total":29,"passed":1,"chamber":"S","chamber_id":94,"url":"https:\/\/legiscan.com\/UT\/rollcall\/HB0065\/id\/1247970","state_link":"https:\/\/le.utah.gov\/DynaBill\/svotes.jsp?sessionid=2023GS&voteid=525&house=S"}],"amendments":[],"supplements":[{"supplement_id":291158,"date":"2023-01-13","type":"Fiscal Note","type_id":1,"title":"Fiscal Note","description":"Fiscal Note HB0065","mime":"application\/pdf","mime_id":2,"url":"https:\/\/legiscan.com\/UT\/supplement\/HB0065\/id\/291158","state_link":"https:\/\/le.utah.gov\/lfa\/fnotes\/2023\/HB0065.fn.pdf","supplement_size":1391666,"supplement_hash":"5efc106a30fbb61bfc7df04f21a19fba"}],"calendar":[{"type_id":1,"type":"Hearing","date":"2023-01-18","time":"14:00","location":"","description":"House Government Operations Hearing"},{"type_id":1,"type":"Hearing","date":"2023-01-25","time":"14:00","location":"","description":"Senate Government Operations and Political Subdivisions Hearing"}]}}