{"roll_call":{"roll_call_id":1251128,"bill_id":1695951,"date":"2023-02-14","desc":"House Education Committee Action (DPA\/SE)","yea":8,"nay":0,"nv":0,"absent":2,"total":10,"passed":1,"chamber":"H","chamber_id":15,"votes":[{"people_id":18652,"vote_id":4,"vote_text":"Absent"},{"people_id":20573,"vote_id":1,"vote_text":"Yea"},{"people_id":21902,"vote_id":1,"vote_text":"Yea"},{"people_id":22292,"vote_id":4,"vote_text":"Absent"},{"people_id":23000,"vote_id":1,"vote_text":"Yea"},{"people_id":24235,"vote_id":1,"vote_text":"Yea"},{"people_id":24236,"vote_id":1,"vote_text":"Yea"},{"people_id":24245,"vote_id":1,"vote_text":"Yea"},{"people_id":24251,"vote_id":1,"vote_text":"Yea"},{"people_id":24254,"vote_id":1,"vote_text":"Yea"}]}}